azure/developer/loadtesting/__init__.py
azure/developer/loadtesting/_client.py
azure/developer/loadtesting/_version.py
azure/developer/loadtesting/py.typed
azure/developer/loadtesting/_generated/__init__.py
azure/developer/loadtesting/_generated/_client.py
azure/developer/loadtesting/_generated/_configuration.py
azure/developer/loadtesting/_generated/_patch.py
azure/developer/loadtesting/_generated/_serialization.py
azure/developer/loadtesting/_generated/_vendor.py
azure/developer/loadtesting/_generated/_version.py
azure/developer/loadtesting/_generated/py.typed
azure/developer/loadtesting/_generated/aio/__init__.py
azure/developer/loadtesting/_generated/aio/_client.py
azure/developer/loadtesting/_generated/aio/_configuration.py
azure/developer/loadtesting/_generated/aio/_patch.py
azure/developer/loadtesting/_generated/aio/_vendor.py
azure/developer/loadtesting/_generated/aio/operations/__init__.py
azure/developer/loadtesting/_generated/aio/operations/_operations.py
azure/developer/loadtesting/_generated/aio/operations/_patch.py
azure/developer/loadtesting/_generated/operations/__init__.py
azure/developer/loadtesting/_generated/operations/_operations.py
azure/developer/loadtesting/_generated/operations/_patch.py
azure/developer/loadtesting/aio/__init__.py
azure/developer/loadtesting/aio/_client.py
azure_developer_loadtesting-1.0.1.dist-info/LICENSE
azure_developer_loadtesting-1.0.1.dist-info/METADATA
azure_developer_loadtesting-1.0.1.dist-info/WHEEL
azure_developer_loadtesting-1.0.1.dist-info/top_level.txt
azure_developer_loadtesting-1.0.1.dist-info/RECORD
